webfriend/__init__.py
webfriend/browser.py
webfriend/cli.py
webfriend/exceptions.py
webfriend/info.py
webfriend/repl.py
webfriend/tab.py
webfriend/rpc/__init__.py
webfriend/rpc/base.py
webfriend/rpc/browser.py
webfriend/rpc/console.py
webfriend/rpc/dom.py
webfriend/rpc/emulation.py
webfriend/rpc/event.py
webfriend/rpc/input.py
webfriend/rpc/inspector.py
webfriend/rpc/network.py
webfriend/rpc/overlay.py
webfriend/rpc/page.py
webfriend/rpc/reply.py
webfriend/rpc/runtime.py
webfriend/rpc/schema.py
webfriend/rpc/target.py
webfriend/scripting/__init__.py
webfriend/scripting/environment.py
webfriend/scripting/execute.py
webfriend/scripting/scope.py
webfriend/scripting/scope_test.py
webfriend/scripting/scripting_test.py
webfriend/scripting/commands/__init__.py
webfriend/scripting/commands/base.py
webfriend/scripting/commands/cookies.py
webfriend/scripting/commands/core.py
webfriend/scripting/commands/file.py
webfriend/scripting/commands/fmt.py
webfriend/scripting/commands/fmt_test.py
webfriend/scripting/commands/page.py
webfriend/scripting/commands/utils.py
webfriend/scripting/commands/vars.py
webfriend/scripting/parser/__init__.py
webfriend/scripting/parser/commands.py
webfriend/scripting/parser/conditions.py
webfriend/scripting/parser/exceptions.py
webfriend/scripting/parser/grammar.py
webfriend/scripting/parser/lang.py
webfriend/scripting/parser/loops.py
webfriend/scripting/parser/pygments.py
webfriend/scripting/parser/types.py
webfriend/scripting/parser/variables.py
webfriend/utils/__init__.py
webfriend/utils/commands.py
webfriend/utils/docs.py
webfriend/utils/patch_json.py
webfriend-0.4.1.dist-info/DESCRIPTION.rst
webfriend-0.4.1.dist-info/METADATA
webfriend-0.4.1.dist-info/RECORD
webfriend-0.4.1.dist-info/WHEEL
webfriend-0.4.1.dist-info/entry_points.txt
webfriend-0.4.1.dist-info/metadata.json
webfriend-0.4.1.dist-info/top_level.txt
