Metadata-Version: 2.0
Name: webfriend
Version: 0.4.1
Summary: An API binding and automation control language for the Chrome Remote Debugging API
Home-page: https://github.com/ghetzel/webfriend
Author: Gary Hetzel
Author-email: garyhetzel@gmail.com
License: UNKNOWN
Platform: UNKNOWN
Requires-Dist: click (==6.7)
Requires-Dist: click-log (<0.2.0)
Requires-Dist: colorlog
Requires-Dist: ephemeral-port-reserve
Requires-Dist: prompt-toolkit
Requires-Dist: pygments (==2.2.0)
Requires-Dist: requests
Requires-Dist: termcolor
Requires-Dist: textx (<1.6)
Requires-Dist: urlnorm
Requires-Dist: websocket-client
